YXKJapi/Tools.py
YXKJapi/__init__.py
YXKJapi/example.py
YXKJapi/test.py
YXKJapi/upAndDown.py
YXKJapi/Scripts/__init__.py
YXKJapi/Scripts/cut.cp38-win_amd64.pyd
YXKJapi/Scripts/down.cp38-win_amd64.pyd
YXKJapi/Scripts/transform.cp38-win_amd64.pyd
YXKJapi/Scripts/water_extract.cp38-win_amd64.pyd
YXKJapi-0.1.0.dist-info/LICENSE
YXKJapi-0.1.0.dist-info/METADATA
YXKJapi-0.1.0.dist-info/WHEEL
YXKJapi-0.1.0.dist-info/top_level.txt
YXKJapi-0.1.0.dist-info/RECORD
