Metadata-Version: 2.1
Name: YXKJapi
Version: 0.1.0
Summary: 遥相科技api测试产品
Home-page: UNKNOWN
Author: bmd
Author-email: 1790523836@qq.com
License: UNKNOWN
Platform: UNKNOWN
Requires-Python: >=3.6
